ndifflib/__init__.py
ndifflib-0.1.0.dist-info/DESCRIPTION.rst
ndifflib-0.1.0.dist-info/METADATA
ndifflib-0.1.0.dist-info/RECORD
ndifflib-0.1.0.dist-info/WHEEL
ndifflib-0.1.0.dist-info/entry_points.txt
ndifflib-0.1.0.dist-info/metadata.json
ndifflib-0.1.0.dist-info/top_level.txt
